plainconf.py
plainconf-0.1.21.dist-info/LICENSE
plainconf-0.1.21.dist-info/METADATA
plainconf-0.1.21.dist-info/WHEEL
plainconf-0.1.21.dist-info/top_level.txt
plainconf-0.1.21.dist-info/RECORD
