Metadata-Version: 2.1
Name: plainconf
Version: 0.1.21
Summary: Minimal configuration handling supporting hashicorp vault.
Author-email: Caspar David Dzikus <caspar@kodekitchen.com>
Project-URL: repository, https://github.com/kodekitchen/plainconf
Project-URL: bugtracker, https://github.com/kodekitchen/plainconf/issues
Keywords: configuration,vault
Classifier: Development Status :: 3 - Alpha
License-File: LICENSE
Requires-Dist: python-dotenv
Requires-Dist: hvac
Requires-Dist: tomli-w
Requires-Dist: cryptography
